<?xml version="1.0" encoding="UTF-8" standalone="yes"?>
<addon id="plugin.video.gallifrey" name="[COLORcyan]Gallifrey[/COLOR]" version="1.4" provider-name="John Smith">
  <requires>
    <import addon="xbmc.python" version="3.0.0" />
    <import addon="script.module.requests" />
    <import addon="script.module.routing"/>
    <import addon="script.module.unidecode" />
    <import addon="script.module.inputstreamhelper" />
    <import addon="script.module.resolveurl"/>
    <!--<import addon="name" />-->
  </requires>
  <extension point="xbmc.python.pluginsource" library="default.py">
    <provides>video</provides>
  </extension>
  <extension point="xbmc.addon.metadata">
    <summary lang="en_GB">Doctor Who Complete Collection All One Click</summary>
    <platform>all</platform>
    <language>en</language>
    <license>Tardis</license>
	<assets>
		<icon>icon.png</icon>
		<fanart>fanart.jpg</fanart>
  </assets>
  </extension>
</addon>